pyconnectedcars/BinarySensor.py
pyconnectedcars/Exceptions.py
pyconnectedcars/Fuel.py
pyconnectedcars/GPS.py
pyconnectedcars/Lock.py
pyconnectedcars/__init__.py
pyconnectedcars/__init__.pyc
pyconnectedcars/connection.py
pyconnectedcars/connection.pyc
pyconnectedcars/controller.py
pyconnectedcars/vehicle.py
pyconnectedcars/__pycache__/BinarySensor.cpython-36.pyc
pyconnectedcars/__pycache__/Exceptions.cpython-36.pyc
pyconnectedcars/__pycache__/Fuel.cpython-36.pyc
pyconnectedcars/__pycache__/GPS.cpython-36.pyc
pyconnectedcars/__pycache__/Lock.cpython-36.pyc
pyconnectedcars/__pycache__/__init__.cpython-36.pyc
pyconnectedcars/__pycache__/connection.cpython-36.pyc
pyconnectedcars/__pycache__/controller.cpython-36.pyc
pyconnectedcars/__pycache__/vehicle.cpython-36.pyc
pyconnectedcars-0.2.1.dist-info/DESCRIPTION.rst
pyconnectedcars-0.2.1.dist-info/METADATA
pyconnectedcars-0.2.1.dist-info/RECORD
pyconnectedcars-0.2.1.dist-info/WHEEL
pyconnectedcars-0.2.1.dist-info/metadata.json
pyconnectedcars-0.2.1.dist-info/top_level.txt
