Metadata-Version: 2.0
Name: pyconnectedcars
Version: 0.2.1
Summary: A library to work with Connected Cars API.
Home-page: https://github.com/DarkFox/pyconnectedcars
Author: Martin Eberhardt
Author-email: martin@darkfox.dk
License: MIT
Platform: UNKNOWN
Classifier: Intended Audience :: Developers
Classifier: Operating System :: OS Independent
Classifier: Programming Language :: Python :: 3
Classifier: Programming Language :: Python :: 3.4
Classifier: Programming Language :: Python :: 3.5
Classifier: Programming Language :: Python :: 3.6
Classifier: Topic :: Internet
Requires-Python: >=3
